{
    "timestamp": "2025-12-13 21:21:22",
    "accessible_count": 49,
    "inaccessible_count": 9,
    "total_count": 58,
    "has_author_link_count": 0,
    "author_url": "blog.liushen.fun",
    "link_status": [
        {
            "name": "Hexo",
            "link": "https://hexo.io/zh-tw/",
            "latency": 0.29,
            "fail_count": 0,
            "has_author_link": false,
            "linkpage": ""
        },
        {
            "name": "anzhiyu主题",
            "link": "https://blog.anheyu.com/",
            "latency": 2.17,
            "fail_count": 0,
            "has_author_link": false,
            "linkpage": ""
        },
        {
            "name": "Butterfly",
            "link": "https://butterfly.js.org/",
            "latency": 0.28,
            "fail_count": 0,
            "has_author_link": false,
            "linkpage": ""
        },
        {
            "name": "安知鱼",
            "link": "https://blog.anheyu.com/",
            "latency": 2.14,
            "fail_count": 0,
            "has_author_link": false,
            "linkpage": ""
        },
        {
            "name": "CMLiusss",
            "link": "https://blog.cmliussss.com",
            "latency": 1.02,
            "fail_count": 0,
            "has_author_link": false,
            "linkpage": ""
        },
        {
            "name": "东方月初",
            "link": "https://blog.biuxin.com",
            "latency": 0.38,
            "fail_count": 0,
            "has_author_link": false,
            "linkpage": ""
        },
        {
            "name": "梦爱吃鱼",
            "link": "https://blog.bsgun.cn/",
            "latency": 1.04,
            "fail_count": 0,
            "has_author_link": false,
            "linkpage": ""
        },
        {
            "name": "清羽飞扬",
            "link": "https://blog.liushen.fun/",
            "latency": 0.58,
            "fail_count": 0,
            "has_author_link": false,
            "linkpage": ""
        },
        {
            "name": "Akilarの糖果屋",
            "link": "https://akilar.top/",
            "latency": 1.24,
            "fail_count": 0,
            "has_author_link": false,
            "linkpage": ""
        },
        {
            "name": "Fomalhaut🥝",
            "link": "https://www.fomal.cc/",
            "latency": 0.47,
            "fail_count": 0,
            "has_author_link": false,
            "linkpage": ""
        },
        {
            "name": "东方月初",
            "link": "https://blog.biuxin.com",
            "latency": 0.1,
            "fail_count": 0,
            "has_author_link": false,
            "linkpage": ""
        },
        {
            "name": "葱苓sama",
            "link": "https://blog.ciraos.top",
            "latency": 2.76,
            "fail_count": 0,
            "has_author_link": false,
            "linkpage": ""
        },
        {
            "name": "Naokuo",
            "link": "https://www.naokuo.top",
            "latency": 1.44,
            "fail_count": 0,
            "has_author_link": false,
            "linkpage": ""
        },
        {
            "name": "一粒微尘",
            "link": "https://blog.667408.xyz",
            "latency": -1,
            "fail_count": 93,
            "has_author_link": false,
            "linkpage": ""
        },
        {
            "name": "安小歪",
            "link": "https://blog.anxy.top/",
            "latency": 1.5,
            "fail_count": 0,
            "has_author_link": false,
            "linkpage": ""
        },
        {
            "name": "青桔气球",
            "link": "https://blog.qjqq.cn/",
            "latency": 2.23,
            "fail_count": 0,
            "has_author_link": false,
            "linkpage": ""
        },
        {
            "name": "煮雪话河山",
            "link": "https://blog.cent1pedee.top/",
            "latency": -1,
            "fail_count": 8,
            "has_author_link": false,
            "linkpage": ""
        },
        {
            "name": "唐志远",
            "link": "https://fe32.top/",
            "latency": -1,
            "fail_count": 33,
            "has_author_link": false,
            "linkpage": ""
        },
        {
            "name": "铭心石刻",
            "link": "https://blog.kouseki.cn/",
            "latency": 2.29,
            "fail_count": 0,
            "has_author_link": false,
            "linkpage": ""
        },
        {
            "name": "小旦",
            "link": "https://satera.cn",
            "latency": 0.33,
            "fail_count": 0,
            "has_author_link": false,
            "linkpage": ""
        },
        {
            "name": "Leonus",
            "link": "https://blog.leonus.cn/",
            "latency": 3.25,
            "fail_count": 0,
            "has_author_link": false,
            "linkpage": ""
        },
        {
            "name": "小智の空间站",
            "link": "https://blog.cuixinyu.com",
            "latency": -1,
            "fail_count": 259,
            "has_author_link": false,
            "linkpage": ""
        },
        {
            "name": "百里飞扬",
            "link": "https://blog.meta-code.top",
            "latency": 2.35,
            "fail_count": 0,
            "has_author_link": false,
            "linkpage": ""
        },
        {
            "name": "山岳库博",
            "link": "https://kmar.top/",
            "latency": 0.86,
            "fail_count": 0,
            "has_author_link": false,
            "linkpage": ""
        },
        {
            "name": "轻笑Chuckle",
            "link": "https://www.qcqx.cn",
            "latency": 0.75,
            "fail_count": 0,
            "has_author_link": false,
            "linkpage": ""
        },
        {
            "name": "isYangs Blog",
            "link": "https://isyangs.cn",
            "latency": -1,
            "fail_count": 155,
            "has_author_link": false,
            "linkpage": ""
        },
        {
            "name": "Spark の Blog",
            "link": "https://www.aspark.cc",
            "latency": 0.68,
            "fail_count": 0,
            "has_author_link": false,
            "linkpage": ""
        },
        {
            "name": "杜老师说",
            "link": "https://dusays.com",
            "latency": 0.11,
            "fail_count": 0,
            "has_author_link": false,
            "linkpage": ""
        },
        {
            "name": "凌尘K-Blog",
            "link": "https://blog.lck68.xyz/",
            "latency": 0.1,
            "fail_count": 0,
            "has_author_link": false,
            "linkpage": ""
        },
        {
            "name": "别亦难",
            "link": "https://lazyingman.cn",
            "latency": 1.55,
            "fail_count": 0,
            "has_author_link": false,
            "linkpage": ""
        },
        {
            "name": "Nuyoah",
            "link": "https://262259.xyz/",
            "latency": -1,
            "fail_count": 332,
            "has_author_link": false,
            "linkpage": ""
        },
        {
            "name": "無名小栈",
            "link": "https://blog.imsyy.top/",
            "latency": 0.41,
            "fail_count": 0,
            "has_author_link": false,
            "linkpage": ""
        },
        {
            "name": "GanSer",
            "link": "https://www.gan1ser.top/",
            "latency": 2.15,
            "fail_count": 0,
            "has_author_link": false,
            "linkpage": ""
        },
        {
            "name": "cosの博客",
            "link": "https://ysx.cosine.ren/",
            "latency": 0.49,
            "fail_count": 0,
            "has_author_link": false,
            "linkpage": ""
        },
        {
            "name": "随风起",
            "link": "https://blog.bywind.xyz/",
            "latency": -1,
            "fail_count": 45,
            "has_author_link": false,
            "linkpage": ""
        },
        {
            "name": "Revincx",
            "link": "https://blog.revincx.icu/",
            "latency": 0.45,
            "fail_count": 0,
            "has_author_link": false,
            "linkpage": ""
        },
        {
            "name": "Calyee",
            "link": "https://blog.calyee.top/",
            "latency": 1.23,
            "fail_count": 0,
            "has_author_link": false,
            "linkpage": ""
        },
        {
            "name": "小冰博客",
            "link": "https://zfe.space/",
            "latency": 1.18,
            "fail_count": 0,
            "has_author_link": false,
            "linkpage": ""
        },
        {
            "name": "IMyself",
            "link": "https://blog.lmyself.top/",
            "latency": 1.06,
            "fail_count": 0,
            "has_author_link": false,
            "linkpage": ""
        },
        {
            "name": "polar-bear～Blog",
            "link": "https://polar-bear.eu.org/",
            "latency": 0.42,
            "fail_count": 0,
            "has_author_link": false,
            "linkpage": ""
        },
        {
            "name": "青云志",
            "link": "https://blog.811520.xyz/",
            "latency": 0.95,
            "fail_count": 0,
            "has_author_link": false,
            "linkpage": ""
        },
        {
            "name": "周润发",
            "link": "https://blog.aizrf.com/",
            "latency": -1,
            "fail_count": 117,
            "has_author_link": false,
            "linkpage": ""
        },
        {
            "name": "又见苍岚",
            "link": "https://www.zywvvd.com",
            "latency": 0.37,
            "fail_count": 0,
            "has_author_link": false,
            "linkpage": ""
        },
        {
            "name": "chfychin",
            "link": "https://blog.chfychin.cn",
            "latency": 0.47,
            "fail_count": 0,
            "has_author_link": false,
            "linkpage": ""
        },
        {
            "name": "Eurkon",
            "link": "https://blog.eurkon.com",
            "latency": 0.28,
            "fail_count": 0,
            "has_author_link": false,
            "linkpage": ""
        },
        {
            "name": "GnaixEuy",
            "link": "https://blog.gnaixeuy.cn/",
            "latency": 0.78,
            "fail_count": 0,
            "has_author_link": false,
            "linkpage": ""
        },
        {
            "name": "爱吃肉的猫",
            "link": "https://meuicat.com/",
            "latency": 0.44,
            "fail_count": 0,
            "has_author_link": false,
            "linkpage": ""
        },
        {
            "name": "李小白",
            "link": "https://cf.lxb.icu/",
            "latency": 0.48,
            "fail_count": 0,
            "has_author_link": false,
            "linkpage": ""
        },
        {
            "name": "青稚の空间",
            "link": "https://blog.linux-qitong.top/",
            "latency": 1.28,
            "fail_count": 0,
            "has_author_link": false,
            "linkpage": ""
        },
        {
            "name": "XingJiのBlog",
            "link": "https://love.xingji.fun/",
            "latency": 0.13,
            "fail_count": 0,
            "has_author_link": false,
            "linkpage": ""
        },
        {
            "name": "Imz’s Blog",
            "link": "https://blog.imz.me/",
            "latency": 0.26,
            "fail_count": 0,
            "has_author_link": false,
            "linkpage": ""
        },
        {
            "name": "KasumiTech",
            "link": "https://sakurablogs.top/",
            "latency": -1,
            "fail_count": 61,
            "has_author_link": false,
            "linkpage": ""
        },
        {
            "name": "胜天半子",
            "link": "https://blog.291055.xyz/",
            "latency": 0.36,
            "fail_count": 0,
            "has_author_link": false,
            "linkpage": ""
        },
        {
            "name": "辣条",
            "link": "https://blog.owwo.fun",
            "latency": 0.76,
            "fail_count": 0,
            "has_author_link": false,
            "linkpage": ""
        },
        {
            "name": "Elykia",
            "link": "https://blog.elykia.cn/",
            "latency": 1.31,
            "fail_count": 0,
            "has_author_link": false,
            "linkpage": ""
        },
        {
            "name": "陵长镜",
            "link": "https://r1n.top",
            "latency": 0.26,
            "fail_count": 0,
            "has_author_link": false,
            "linkpage": ""
        },
        {
            "name": "大爱无痕",
            "link": "https://blog.youngboy.top/",
            "latency": 0.3,
            "fail_count": 0,
            "has_author_link": false,
            "linkpage": ""
        },
        {
            "name": "Fantasy`Ke Blog",
            "link": "https://blog.fantasyke.cn/",
            "latency": 1.25,
            "fail_count": 0,
            "has_author_link": false,
            "linkpage": ""
        }
    ]
}